mite/__init__.py
mite/__main__.py
mite/_version.py
mite/collector.py
mite/config.py
mite/context.py
mite/controller.py
mite/datapools.py
mite/example.py
mite/exceptions.py
mite/har_to_mite.py
mite/logoutput.py
mite/nanomsg.py
mite/recorder.py
mite/runner.py
mite/s3datapools.py
mite/scenario.py
mite/stats.py
mite/test.py
mite/utils.py
mite/volume_model.py
mite/zmq.py
mite/cli/__init__.py
mite/cli/cat.py
mite/cli/collector.py
mite/cli/common.py
mite/cli/duplicator.py
mite/cli/receiver.py
mite/cli/stats.py
mite/cli/test.py
mite/otel/__init__.py
mite/otel/acurl_integration.py
mite/otel/config.py
mite/otel/context.py
mite/otel/context_integration.py
mite/otel/instrumentation.py
mite/otel/tracing.py
mite/web/__init__.py
mite/web/prometheus.py
mite_amqp/__init__.py
mite_browser/__init__.py
mite_db_datapool/README.md
mite_db_datapool/__init__.py
mite_db_datapool/db_to_pool.py
mite_db_datapool/mite_db_example.py
mite_finagle/README.md
mite_finagle/__init__.py
mite_finagle/mux.py
mite_finagle/stats.py
mite_finagle/thrift.py
mite_finagle/tests/__init__.py
mite_finagle/tests/conftest.py
mite_finagle/tests/foo_service.thrift
mite_finagle/tests/test_integration.py
mite_finagle/tests/test_mux.py
mite_finagle/tests/test_thrift.py
mite_finagle/tests/foo_service/Foo-remote
mite_finagle/tests/foo_service/Foo.py
mite_finagle/tests/foo_service/__init__.py
mite_finagle/tests/foo_service/constants.py
mite_finagle/tests/foo_service/ttypes.py
mite_http/__init__.py
mite_http/stats.py
mite_kafka/__init__.py
mite_kafka/mite_kafka_example.py
mite_kafka/stats.py
mite_playwright/README.md
mite_playwright/__init__.py
mite_playwright/mite_playwright_example.py
mite_playwright/stats.py
mite_selenium/__init__.py
mite_selenium/stats.py
mite_websocket/__init__.py
mite-2.9.2.dist-info/METADATA
mite-2.9.2.dist-info/WHEEL
mite-2.9.2.dist-info/entry_points.txt
mite-2.9.2.dist-info/licenses/LICENSE
mite-2.9.2.dist-info/RECORD
