Metadata-Version: 2.4
Name: mite
Version: 2.9.2
Summary: A Python Performance Testing Framework
Project-URL: Homepage, https://github.com/sky-uk/mite/
Project-URL: Documentation, https://sky-uk.github.io/mite/
Project-URL: Repository, https://github.com/sky-uk/mite/
Project-URL: Issues, https://github.com/sky-uk/mite/issues
Author-email: Sky UK <mite@sky.uk>
License-Expression: MIT
License-File: LICENSE
Classifier: Operating System :: POSIX :: Linux
Classifier: Programming Language :: Python
Classifier: Programming Language :: Python :: 3
Classifier: Programming Language :: Python :: 3.10
Classifier: Programming Language :: Python :: 3.11
Classifier: Programming Language :: Python :: 3.12
Classifier: Programming Language :: Python :: 3.13
Requires-Python: <3.14,>=3.10
Requires-Dist: acurl
Requires-Dist: aio-pika
Requires-Dist: aiokafka
Requires-Dist: boto3
Requires-Dist: bs4
Requires-Dist: docopt
Requires-Dist: flask
Requires-Dist: jinja2
Requires-Dist: msgpack
Requires-Dist: nanomsg
Requires-Dist: prettytable
Requires-Dist: pyzmq
Requires-Dist: selenium-wire==4.6.5
Requires-Dist: selenium<4
Requires-Dist: sqlalchemy
Requires-Dist: thrift
Requires-Dist: ujson
Requires-Dist: uvloop>=0.21.0
Requires-Dist: websockets
Provides-Extra: dev
Requires-Dist: cython>=3.0; extra == 'dev'
Requires-Dist: httpbin>=0.10.2; extra == 'dev'
Requires-Dist: hypothesis; extra == 'dev'
Requires-Dist: pytest; extra == 'dev'
Requires-Dist: pytest-asyncio; extra == 'dev'
Requires-Dist: pytest-cov; extra == 'dev'
Requires-Dist: pytest-httpbin; extra == 'dev'
Requires-Dist: pytest-httpserver; extra == 'dev'
Requires-Dist: ruff>=0.1.0; extra == 'dev'
Requires-Dist: werkzeug==3.1.3; extra == 'dev'
Provides-Extra: otel
Requires-Dist: opentelemetry-api>=1.20.0; extra == 'otel'
Requires-Dist: opentelemetry-exporter-otlp-proto-grpc>=1.20.0; extra == 'otel'
Requires-Dist: opentelemetry-exporter-otlp-proto-http>=1.20.0; extra == 'otel'
Requires-Dist: opentelemetry-exporter-zipkin>=1.20.0; extra == 'otel'
Requires-Dist: opentelemetry-sdk>=1.20.0; extra == 'otel'
